thealphavideo/Jenkinsfile
thealphavideo/README.md
thealphavideo/README.rst
thealphavideo/__init__.py
thealphavideo/__main__.py
thealphavideo/app.json
thealphavideo/azure-pipelines.yml
thealphavideo/build.spec
thealphavideo/ci.sh
thealphavideo/database.db
thealphavideo/doc.yml
thealphavideo/init_db.py
thealphavideo/interaction.json
thealphavideo/keypack.pyu
thealphavideo/logo.ico
thealphavideo/pages.py
thealphavideo/public.py
thealphavideo/requirements.txt
thealphavideo/runtime.txt
thealphavideo/schema.sql
thealphavideo/templates.yaml
thealphavideo/updater.py
thealphavideo/win.spec
thealphavideo/windows-alpha-video.py
thealphavideo-1.49.dist-info/LICENSE
thealphavideo-1.49.dist-info/METADATA
thealphavideo-1.49.dist-info/WHEEL
thealphavideo-1.49.dist-info/entry_points.txt
thealphavideo-1.49.dist-info/top_level.txt
thealphavideo-1.49.dist-info/RECORD
